MANIFEST.in
README.rst
setup.cfg
setup.py
config_parser/__init__.py
config_parser/conversions.py
config_parser/enums.py
config_parser/exceptions.py
config_parser/helpers.py
config_parser/parser.py
examples/__init__.py
examples/main.py
py_config_parser.egg-info/PKG-INFO
py_config_parser.egg-info/SOURCES.txt
py_config_parser.egg-info/dependency_links.txt
py_config_parser.egg-info/top_level.txt