Metadata-Version: 1.1
Name: py-config-parser
Version: 2.0.1
Summary: Simple python json configuration file parser
Home-page: https://github.com/damirazo/py-config-parser
Author: damirazo
Author-email: me@damirazo.ru
License: MIT
Keywords: config parser json
Platform: UNKNOWN
Classifier: Development Status :: 5 - Production/Stable
Classifier: Intended Audience :: Developers
Classifier: Topic :: Software Development :: Code Generators
Classifier: License :: OSI Approved :: MIT License
Classifier: Programming Language :: Python :: 3.5
Classifier: Programming Language :: Python :: 3.6
